rocket_framework/__init__.py
rocket_framework/base_model.py
rocket_framework/clickhouse.py
rocket_framework/coding.py
rocket_framework/config.py
rocket_framework/crypto.py
rocket_framework/csv.py
rocket_framework/dict.py
rocket_framework/es.py
rocket_framework/excel.py
rocket_framework/file.py
rocket_framework/host.py
rocket_framework/http.py
rocket_framework/json.py
rocket_framework/log.py
rocket_framework/memcached.py
rocket_framework/mongodb.py
rocket_framework/mysql.py
rocket_framework/notice.py
rocket_framework/os.py
rocket_framework/powerjob.py
rocket_framework/qr_code.py
rocket_framework/redis.py
rocket_framework/sign.py
rocket_framework/time.py
rocket_framework/uuid.py
rocket_framework/wechat.py
rocket_framework/console/__init__.py
rocket_framework/console/base_console.py
rocket_framework/message_queue/__init__.py
rocket_framework/message_queue/rabbit.py
rocket_framework/message_queue/rocket.py
rocket_framework/web_tornado/__init__.py
rocket_framework/web_tornado/base_tornado.py
rocket_framework/web_tornado/monitor.py
rocket_framework/web_tornado/base_handler/__init__.py
rocket_framework/web_tornado/base_handler/base_api_handler.py
rocket_framework/web_tornado/base_handler/base_cookie_handler.py
rocket_framework/web_tornado/base_handler/base_handler.py
rocket_framework-1.0.1b1.dist-info/licenses/LICENSE
rocket_framework-1.0.1b1.dist-info/METADATA
rocket_framework-1.0.1b1.dist-info/WHEEL
rocket_framework-1.0.1b1.dist-info/top_level.txt
rocket_framework-1.0.1b1.dist-info/RECORD
