Metadata-Version: 2.4
Name: rocket_framework
Version: 1.0.1b1
Summary: rocket framework
Home-page: https://gitee.com/rocket_man/rocket_framework.git
Author: rocket_man
Author-email: rocket@ggo9.com
License: MIT
Classifier: Topic :: Software Development :: Libraries :: Python Modules
Classifier: Programming Language :: Python
Classifier: Programming Language :: Python :: 3.10
Classifier: Programming Language :: Python :: 3.11
Classifier: Programming Language :: Python :: 3.12
Classifier: Programming Language :: Python :: 3.13
Classifier: Programming Language :: Python :: 3.14
Classifier: Programming Language :: Python :: 3.15
Requires-Python: ~=3.4
License-File: LICENSE
Requires-Dist: requests>=2.23.0
Requires-Dist: PyMySQL>=1.0.2
Requires-Dist: python_dateutil>=2.8.1
Requires-Dist: redis>=5.0.7
Requires-Dist: pycryptodome>=3.8.0
Requires-Dist: tornado>=6.5.4
Requires-Dist: bleach>=3.1.5
Requires-Dist: pycket>=0.3.0
Requires-Dist: oss2>=2.13.1
Requires-Dist: cos-python-sdk-v5>=1.9.0
Requires-Dist: DBUtils==1.3
Requires-Dist: openpyxl>=3.0.3
Requires-Dist: xlwt>=1.3.0
Requires-Dist: xlrd>=1.2.0
Requires-Dist: xlutils>=2.0.0
Requires-Dist: qrcode>=6.1
Requires-Dist: Pillow>=7.1.2
Requires-Dist: threadpool>=1.3.2
Requires-Dist: filechunkio>=1.8
Requires-Dist: clickhouse-driver>=0.2.0
Requires-Dist: lxml>=4.5.0
Requires-Dist: numpy>=1.23.5
Requires-Dist: filetype>=1.2.0
Requires-Dist: urllib3==1.26.15
Requires-Dist: nacos-sdk-python==1.0.0
Dynamic: author
Dynamic: author-email
Dynamic: classifier
Dynamic: description
Dynamic: description-content-type
Dynamic: home-page
Dynamic: license
Dynamic: license-file
Dynamic: requires-dist
Dynamic: requires-python
Dynamic: summary
